domovoy/__init__.py
domovoy/app.py
domovoy/cli.py
domovoy/applications/__init__.py
domovoy/applications/registration.py
domovoy/applications/types.py
domovoy/core/__init__.py
domovoy/core/app_infra.py
domovoy/core/configuration.py
domovoy/core/context.py
domovoy/core/errors.py
domovoy/core/task_utils.py
domovoy/core/utils.py
domovoy/core/dependency_tracking/deepreload.py
domovoy/core/dependency_tracking/dependency_tracker.py
domovoy/core/dependency_tracking/file_watcher.py
domovoy/core/engine/active_engine.py
domovoy/core/engine/engine.py
domovoy/core/logging/__init__.py
domovoy/core/logging/http_json.py
domovoy/core/logging/logger_adapter_with_trace.py
domovoy/core/services/callback_register.py
domovoy/core/services/event_listener.py
domovoy/core/services/pip_dependencies.py
domovoy/core/services/service.py
domovoy/core/services/webapi/__init__.py
domovoy/core/services/webapi/schema.py
domovoy/plugins/__init__.py
domovoy/plugins/plugins.py
domovoy/plugins/callbacks/__init__.py
domovoy/plugins/callbacks/entity_listener_callbacks.py
domovoy/plugins/callbacks/event_listener_callbacks.py
domovoy/plugins/hass/__init__.py
domovoy/plugins/hass/api.py
domovoy/plugins/hass/apps.py
domovoy/plugins/hass/core.py
domovoy/plugins/hass/domains.py
domovoy/plugins/hass/entity_id.py
domovoy/plugins/hass/exceptions.py
domovoy/plugins/hass/parsing.py
domovoy/plugins/hass/types.py
domovoy/plugins/hass/typing/apps.py
domovoy/plugins/hass/typing/entities.py
domovoy/plugins/hass/typing/services.py
domovoy/plugins/logger/__init__.py
domovoy/plugins/meta/__init__.py
domovoy/plugins/servents/__init__.py
domovoy/plugins/servents/entities.py
domovoy/plugins/servents/exceptions.py
domovoy/plugins/time/__init__.py
domovoy/plugins/utils/__init__.py
domovoy-0.11.0.dist-info/METADATA
domovoy-0.11.0.dist-info/WHEEL
domovoy-0.11.0.dist-info/licenses/LICENSE
domovoy-0.11.0.dist-info/RECORD
