Metadata-Version: 2.4
Name: domovoy
Version: 0.11.0
Author: carlos-sarmiento
License-File: LICENSE
Requires-Python: >=3.14.2
Requires-Dist: aiohttp>=3.10.5
Requires-Dist: apscheduler>=3.10.1
Requires-Dist: astral>=3.2
Requires-Dist: coloredlogs>=15.0.1
Requires-Dist: cron-converter>=1.2.1
Requires-Dist: domovoy-typing>=2026.1.0
Requires-Dist: idna>=3.7
Requires-Dist: importlab>=0.8
Requires-Dist: orjson>=3.10.6
Requires-Dist: pyserde[yaml]>=0.23.0
Requires-Dist: python-dateutil>=2.8.2
Requires-Dist: pytz~=2024.2
Requires-Dist: pyyaml>=6.0
Requires-Dist: requests<3,>=2.32.3
Requires-Dist: servents-data-model>=0.6.0
Requires-Dist: strawberry-graphql>=0.241.0
Requires-Dist: watchdog>=5.0.2
Requires-Dist: websockets>=12.0
